setup.py
fan/__init__.py
fan/asynchronous.py
fan/context.py
fan/discovery.py
fan/exceptions.py
fan/lifecycle.py
fan/process.py
fan/remote.py
fan/rpc.py
fan/service.py
fan/sync.py
fan/utils.py
fan.egg-info/PKG-INFO
fan.egg-info/SOURCES.txt
fan.egg-info/dependency_links.txt
fan.egg-info/entry_points.txt
fan.egg-info/requires.txt
fan.egg-info/top_level.txt
fan/contrib/__init__.py
fan/contrib/aio/__init__.py
fan/contrib/aio/application.py
fan/contrib/aio/discovery.py
fan/contrib/aio/lifecycle.py
fan/contrib/aio/process.py
fan/contrib/aio/remote.py
fan/contrib/aio/service.py
fan/contrib/aio/tests/__init__.py
fan/contrib/aio/tests/test_lifecycle.py
fan/contrib/aio/tests/test_zk.py
fan/contrib/amqp/__init__.py
fan/contrib/amqp/tests/__init__.py
fan/contrib/amqp/tests/test_amqp.py
fan/contrib/django/__init__.py
fan/contrib/django/span_formatter.py
fan/contrib/kazoo/__init__.py
fan/contrib/kazoo/discovery.py
fan/contrib/redis/__init__.py
fan/contrib/redis/tests/__init__.py
fan/contrib/redis/tests/test_redis_transport.py
fan/contrib/sync_helper/__init__.py
fan/contrib/sync_helper/fan_register.py
fan/contrib/sync_helper/sanic_helpers.py
fan/contrib/sync_helper/examples/__init__.py
fan/contrib/sync_helper/examples/service_client.py
fan/contrib/sync_helper/examples/service_one.py
fan/contrib/sync_helper/examples/service_two.py
fan/contrib/sync_helper/tests/__init__.py
fan/contrib/sync_helper/tests/test_integration_sanic_service_helper.py
fan/contrib/sync_helper/tests/test_sync_helper.py
fan/scripts/__init__.py
fan/scripts/fan.py
fan/tests/__init__.py
fan/tests/test_common.py
fan/tests/test_lifecycle.py
fan/tests/test_service.py
fan/tests/test_service_group.py
fan/tests/test_transport.py
fan/transport/__init__.py