Metadata-Version: 1.0
Name: fan
Version: 0.18.0
Summary: microservices kit
Home-page: https://github.com/micro-fan/fan
Author: cybergrind
Author-email: cybergrind@gmail.com
License: UNKNOWN
Keywords: rpc,microservices
Platform: UNKNOWN
